odoo/addons/sale_commission_settlement_partial_invoice/README.rst
odoo/addons/sale_commission_settlement_partial_invoice/__init__.py
odoo/addons/sale_commission_settlement_partial_invoice/__manifest__.py
odoo/addons/sale_commission_settlement_partial_invoice/i18n/it.po
odoo/addons/sale_commission_settlement_partial_invoice/i18n/sale_commission_settlement_partial_invoice.pot
odoo/addons/sale_commission_settlement_partial_invoice/migrations/12.0.2.0.0/post-migration.py
odoo/addons/sale_commission_settlement_partial_invoice/models/__init__.py
odoo/addons/sale_commission_settlement_partial_invoice/models/invoice.py
odoo/addons/sale_commission_settlement_partial_invoice/models/settlement.py
odoo/addons/sale_commission_settlement_partial_invoice/readme/CONTRIBUTORS.rst
odoo/addons/sale_commission_settlement_partial_invoice/readme/DESCRIPTION.rst
odoo/addons/sale_commission_settlement_partial_invoice/readme/USAGE.rst
odoo/addons/sale_commission_settlement_partial_invoice/static/description/icon.png
odoo/addons/sale_commission_settlement_partial_invoice/static/description/index.html
odoo/addons/sale_commission_settlement_partial_invoice/tests/__init__.py
odoo/addons/sale_commission_settlement_partial_invoice/tests/test_settlement_partial_invoice.py
odoo/addons/sale_commission_settlement_partial_invoice/views/settlement_views.xml
odoo12_addon_sale_commission_settlement_partial_invoice-12.0.2.0.0.99.dev6.dist-info/METADATA
odoo12_addon_sale_commission_settlement_partial_invoice-12.0.2.0.0.99.dev6.dist-info/WHEEL
odoo12_addon_sale_commission_settlement_partial_invoice-12.0.2.0.0.99.dev6.dist-info/top_level.txt
odoo12_addon_sale_commission_settlement_partial_invoice-12.0.2.0.0.99.dev6.dist-info/RECORD
