Metadata-Version: 2.1
Name: odoo12-addon-sale-commission-settlement-partial-invoice
Version: 12.0.2.0.0.99.dev6
Summary: Allow to generate partial agent invoice from settlement
Home-page: https://github.com/OCA/commission
Author: TAKOBI, Odoo Community Association (OCA)
Author-email: support@odoo-community.org
License: AGPL-3
Platform: UNKNOWN
Classifier: Programming Language :: Python
Classifier: Framework :: Odoo
Classifier: Framework :: Odoo :: 12.0
Classifier: License :: OSI Approved :: GNU Affero General Public License v3
Classifier: Development Status :: 4 - Beta
Requires-Python: >=3.5
Requires-Dist: odoo12-addon-sale-commission
Requires-Dist: odoo <12.1dev,>=12.0a
